tests/__init__.py
tests/test_hash_history.py
wattro_sync/__init__.py
wattro_sync/helpers.py
wattro_sync/setup.py
wattro_sync/sync.py
wattro_sync/api/__init__.py
wattro_sync/api/api_mapping.py
wattro_sync/api/mail.py
wattro_sync/api/mosaik_api.py
wattro_sync/api/odbc_api.py
wattro_sync/api/rest_api.py
wattro_sync/api/sqlite_api.py
wattro_sync/api/src_cli.py
wattro_sync/api/topkontor_api.py
wattro_sync/config_reader/__init__.py
wattro_sync/config_reader/access.py
wattro_sync/config_reader/types.py
wattro_sync/file_access/__init__.py
wattro_sync/file_access/logging.py
wattro_sync/file_access/read_write.py
wattro_sync/hash_history/__init__.py
wattro_sync/hash_history/history.py
wattro_sync-0.3.1.dist-info/LICENSE
wattro_sync-0.3.1.dist-info/METADATA
wattro_sync-0.3.1.dist-info/WHEEL
wattro_sync-0.3.1.dist-info/top_level.txt
wattro_sync-0.3.1.dist-info/RECORD
