Metadata-Version: 2.1
Name: wattro-sync
Version: 0.3.1
Summary: Script collection to sync data from local sources to a wattro node
Home-page: https://github.com/wattro/wattro_sync
Author: Wattro GmbH
Author-email: admin@wattro.de
License: MIT License
License-File: LICENSE
Requires-Dist: requests
Requires-Dist: sendgrid
Requires-Dist: simple-term-menu
Requires-Dist: pyodbc
